ghasandbox/__init__.py
ghasandbox/sandbox.py
ghasandbox/version.py
GitHub_Actions_Sandbox-0.0.3.dist-info/LICENSE
GitHub_Actions_Sandbox-0.0.3.dist-info/METADATA
GitHub_Actions_Sandbox-0.0.3.dist-info/WHEEL
GitHub_Actions_Sandbox-0.0.3.dist-info/top_level.txt
GitHub_Actions_Sandbox-0.0.3.dist-info/RECORD
